bank_of_england.py
bank_of_england-0.0.1.dist-info/LICENSE
bank_of_england-0.0.1.dist-info/METADATA
bank_of_england-0.0.1.dist-info/WHEEL
bank_of_england-0.0.1.dist-info/top_level.txt
bank_of_england-0.0.1.dist-info/RECORD
